add_juniper_software/__init__.py
add_juniper_software/add_juniper_software.py
add_juniper_software-1.0.3.dist-info/LICENSE
add_juniper_software-1.0.3.dist-info/METADATA
add_juniper_software-1.0.3.dist-info/WHEEL
add_juniper_software-1.0.3.dist-info/entry_points.txt
add_juniper_software-1.0.3.dist-info/top_level.txt
add_juniper_software-1.0.3.dist-info/zip-safe
add_juniper_software-1.0.3.dist-info/RECORD
